{
  "project_info": {
    "project_number": "799936315484",
    "firebase_url": "https://teams-academy-default-rtdb.firebaseio.com",
    "project_id": "teams-academy",
    "storage_bucket": "teams-academy.appspot.com"
  },
  "client": [
    {
      "client_info": {
        "mobilesdk_app_id": "1:799936315484:android:657c88cbb64bf88cc5e699",
        "android_client_info": {
          "package_name": "com.teamsacademy.teams_academy"
        }
      },
      "oauth_client": [],
      "api_key": [
        {
          "current_key": "AIzaSyAwVmocAIoU3PkmodBzKrkph_UIQWqahL8"
        }
      ],
      "services": {
        "appinvite_service": {
          "other_platform_oauth_client": []
        }
      }
    }
  ],
  "configuration_version": "1"
}